ctyunsdk_eip20220909/__init__.py
ctyunsdk_eip20220909/eip_client.py
ctyunsdk_eip20220909/models/__init__.py
ctyunsdk_eip20220909/models/v4_eip_associate.py
ctyunsdk_eip20220909/models/v4_eip_attach_port_bm.py
ctyunsdk_eip20220909/models/v4_eip_attach_port_vm.py
ctyunsdk_eip20220909/models/v4_eip_change_name.py
ctyunsdk_eip20220909/models/v4_eip_create.py
ctyunsdk_eip20220909/models/v4_eip_delete.py
ctyunsdk_eip20220909/models/v4_eip_disassociate.py
ctyunsdk_eip20220909/models/v4_eip_new_list.py
ctyunsdk_eip20220909/models/v4_eip_show.py
ctyunsdk_eip20220909-2.0.1.dist-info/licenses/LICENSE.txt
ctyunsdk_eip20220909-2.0.1.dist-info/METADATA
ctyunsdk_eip20220909-2.0.1.dist-info/WHEEL
ctyunsdk_eip20220909-2.0.1.dist-info/top_level.txt
ctyunsdk_eip20220909-2.0.1.dist-info/RECORD
